wuchangbin_mcp_demo/__init__.py
wuchangbin_mcp_demo-0.1.0.dist-info/METADATA
wuchangbin_mcp_demo-0.1.0.dist-info/WHEEL
wuchangbin_mcp_demo-0.1.0.dist-info/entry_points.txt
wuchangbin_mcp_demo-0.1.0.dist-info/RECORD
