Metadata-Version: 2.4
Name: wuchangbin-mcp-demo
Version: 0.1.0
Summary: Add your description here
Author-email: binzi <15830091676@163.com>
Requires-Python: >=3.13
Requires-Dist: mcp[cli]>=1.13.1
